xmppgcm/gcm.py
xmppgcm/__init__.py
xmppgcm-0.1.dist-info/DESCRIPTION.rst
xmppgcm-0.1.dist-info/METADATA
xmppgcm-0.1.dist-info/metadata.json
xmppgcm-0.1.dist-info/RECORD
xmppgcm-0.1.dist-info/top_level.txt
xmppgcm-0.1.dist-info/WHEEL
